LICENSE
MANIFEST.in
README.md
setup.cfg
setup.py
Excel_Driver/__init__.py
Excel_Driver/excel.py
Excel_Driver.egg-info/PKG-INFO
Excel_Driver.egg-info/SOURCES.txt
Excel_Driver.egg-info/dependency_links.txt
Excel_Driver.egg-info/requires.txt
Excel_Driver.egg-info/top_level.txt
excel_driver/__init__.py
excel_driver/excel.py