Metadata-Version: 1.0
Name: Excel-Driver
Version: 0.0.1
Summary: a driver excel tool
Home-page: https://github.com/xuehongbo/test_tool
Author: HongBo Xue
Author-email: 505386086@qq.com
License: MIT License
Keywords: driver excel
Platform: any
